_black_version.py
_black_version.pyi
black/__init__.py
black/__main__.py
black/_width_table.py
black/brackets.py
black/cache.py
black/comments.py
black/concurrency.py
black/const.py
black/debug.py
black/files.py
black/handle_ipynb_magics.py
black/linegen.py
black/lines.py
black/mode.py
black/nodes.py
black/numerics.py
black/output.py
black/parsing.py
black/py.typed
black/ranges.py
black/report.py
black/rusty.py
black/schema.py
black/strings.py
black/trans.py
black/resources/__init__.py
black/resources/black.schema.json
blackd/__init__.py
blackd/__main__.py
blackd/client.py
blackd/middlewares.py
blib2to3/Grammar.txt
blib2to3/LICENSE
blib2to3/PatternGrammar.txt
blib2to3/README
blib2to3/__init__.py
blib2to3/pygram.py
blib2to3/pytree.py
blib2to3/pgen2/__init__.py
blib2to3/pgen2/conv.py
blib2to3/pgen2/driver.py
blib2to3/pgen2/grammar.py
blib2to3/pgen2/literals.py
blib2to3/pgen2/parse.py
blib2to3/pgen2/pgen.py
blib2to3/pgen2/token.py
blib2to3/pgen2/tokenize.py
black_cobaltt7_test-26.1a4.dist-info/METADATA
black_cobaltt7_test-26.1a4.dist-info/WHEEL
black_cobaltt7_test-26.1a4.dist-info/entry_points.txt
black_cobaltt7_test-26.1a4.dist-info/licenses/LICENSE
black_cobaltt7_test-26.1a4.dist-info/RECORD
